desktop_entry_lib/__init__.py
desktop_entry_lib/py.typed
desktop_entry_lib-5.0.dist-info/LICENSE
desktop_entry_lib-5.0.dist-info/METADATA
desktop_entry_lib-5.0.dist-info/WHEEL
desktop_entry_lib-5.0.dist-info/top_level.txt
desktop_entry_lib-5.0.dist-info/RECORD
