Metadata-Version: 2.1
Name: desktop-entry-lib
Version: 5.0
Summary: A library for working with .desktop files
Author-email: JakobDev <jakobdev@gmx.de>
License: BSD-2-Clause
Project-URL: Source, https://codeberg.org/JakobDev/desktop-entry-lib
Project-URL: Issues, https://codeberg.org/JakobDev/desktop-entry-lib/issues
Project-URL: Documentation, https://desktop-entry-lib.readthedocs.io
Project-URL: Donation, https://ko-fi.com/jakobdev
Keywords: JakobDev,Linux,Freedesktop,.desktop
Classifier: Development Status :: 5 - Production/Stable
Classifier: Intended Audience :: Developers
Classifier: Environment :: Other Environment
Classifier: License :: OSI Approved :: BSD License
Classifier: Operating System :: POSIX
Classifier: Operating System :: POSIX :: BSD
Classifier: Operating System :: POSIX :: Linux
Classifier: Programming Language :: Python :: 3
Classifier: Programming Language :: Python :: 3.10
Classifier: Programming Language :: Python :: 3.11
Classifier: Programming Language :: Python :: 3.12
Classifier: Programming Language :: Python :: 3 :: Only
Classifier: Programming Language :: Python :: Implementation :: CPython
Classifier: Programming Language :: Python :: Implementation :: PyPy
Classifier: Typing :: Typed
Requires-Python: >=3.10
License-File: LICENSE
Provides-Extra: xdg-desktop-portal
Requires-Dist: jeepney ; extra == 'xdg-desktop-portal'
